gpt/__init__.py
gpt/openai/__init__.py
gpt/openai/chat_completion.py
llm_base-0.0.2.dist-info/METADATA
llm_base-0.0.2.dist-info/WHEEL
llm_base-0.0.2.dist-info/top_level.txt
llm_base-0.0.2.dist-info/RECORD
